LICENSE
README.md
setup.cfg
setup.py
albaem/__init__.py
albaem/core.py
albaem.egg-info/PKG-INFO
albaem.egg-info/SOURCES.txt
albaem.egg-info/dependency_links.txt
albaem.egg-info/entry_points.txt
albaem.egg-info/requires.txt
albaem.egg-info/top_level.txt
albaem.egg-info/zip-safe
albaem/tango/__init__.py
albaem/tango/server/__init__.py
albaem/tango/server/device.py